streamlit_execute/__init__.py
streamlit_execute/example.py
streamlit_execute/frontend/dist/index.html
streamlit_execute/frontend/dist/vite.svg
streamlit_execute/frontend/dist/assets/README.md
streamlit_execute/frontend/dist/assets/__vite-browser-external-BIHI7g3E.js
streamlit_execute/frontend/dist/assets/console.html
streamlit_execute/frontend/dist/assets/ffi.d.ts
streamlit_execute/frontend/dist/assets/index-CTtX0wtW.js
streamlit_execute/frontend/dist/assets/package.json
streamlit_execute/frontend/dist/assets/pyodide-lock.json
streamlit_execute/frontend/dist/assets/pyodide.asm.js
streamlit_execute/frontend/dist/assets/pyodide.asm.wasm
streamlit_execute/frontend/dist/assets/pyodide.d.ts
streamlit_execute/frontend/dist/assets/pyodide.js
streamlit_execute/frontend/dist/assets/pyodide.js.map
streamlit_execute/frontend/dist/assets/pyodide.mjs
streamlit_execute/frontend/dist/assets/pyodide.mjs.map
streamlit_execute/frontend/dist/assets/python_stdlib.zip
streamlit_execute/frontend_m/dist/index.html
streamlit_execute/frontend_m/dist/vite.svg
streamlit_execute/frontend_m/dist/assets/index-Dt6B85vX.js
streamlit_execute-0.1.0.dist-info/LICENSE
streamlit_execute-0.1.0.dist-info/METADATA
streamlit_execute-0.1.0.dist-info/WHEEL
streamlit_execute-0.1.0.dist-info/top_level.txt
streamlit_execute-0.1.0.dist-info/RECORD
