Metadata-Version: 2.1
Name: streamlit-execute
Version: 0.1.0
Summary: Streamlit component that allows you to execute Python code using Pyodide.
Home-page: 
Author: Anas Bouzid
Author-email: anasbouzid@gmail.com
License: UNKNOWN
Platform: UNKNOWN
Requires-Python: >=3.7
License-File: LICENSE
Requires-Dist: streamlit (>=0.63)
